youtube_community_tab/__init__.py
youtube_community_tab/comment.py
youtube_community_tab/community_tab.py
youtube_community_tab/post.py
youtube_community_tab/reply.py
youtube_community_tab/requests_handler.py
youtube_community_tab/helpers/__init__.py
youtube_community_tab/helpers/clean_items.py
youtube_community_tab/helpers/utils.py
youtube_community_tab-0.2.3.2.1.dist-info/LICENSE
youtube_community_tab-0.2.3.2.1.dist-info/METADATA
youtube_community_tab-0.2.3.2.1.dist-info/WHEEL
youtube_community_tab-0.2.3.2.1.dist-info/top_level.txt
youtube_community_tab-0.2.3.2.1.dist-info/RECORD
