Metadata-Version: 2.1
Name: youtube-community-tab
Version: 0.2.3.2.1
Summary: A python3 module to handle YouTube Community Tab
Home-page: https://github.com/bot-jonas/youtube-community-tab
License: UNKNOWN
Platform: UNKNOWN
License-File: LICENSE
Requires-Dist: requests-cache
